odoo/addons/sale_automatic_workflow/README.rst
odoo/addons/sale_automatic_workflow/__init__.py
odoo/addons/sale_automatic_workflow/__manifest__.py
odoo/addons/sale_automatic_workflow/data/automatic_workflow_data.xml
odoo/addons/sale_automatic_workflow/i18n/am.po
odoo/addons/sale_automatic_workflow/i18n/ar.po
odoo/addons/sale_automatic_workflow/i18n/bg.po
odoo/addons/sale_automatic_workflow/i18n/bs.po
odoo/addons/sale_automatic_workflow/i18n/ca.po
odoo/addons/sale_automatic_workflow/i18n/ca_ES.po
odoo/addons/sale_automatic_workflow/i18n/cs.po
odoo/addons/sale_automatic_workflow/i18n/da.po
odoo/addons/sale_automatic_workflow/i18n/de.po
odoo/addons/sale_automatic_workflow/i18n/el_GR.po
odoo/addons/sale_automatic_workflow/i18n/en_GB.po
odoo/addons/sale_automatic_workflow/i18n/es.po
odoo/addons/sale_automatic_workflow/i18n/es_AR.po
odoo/addons/sale_automatic_workflow/i18n/es_CL.po
odoo/addons/sale_automatic_workflow/i18n/es_CO.po
odoo/addons/sale_automatic_workflow/i18n/es_CR.po
odoo/addons/sale_automatic_workflow/i18n/es_DO.po
odoo/addons/sale_automatic_workflow/i18n/es_EC.po
odoo/addons/sale_automatic_workflow/i18n/es_ES.po
odoo/addons/sale_automatic_workflow/i18n/es_MX.po
odoo/addons/sale_automatic_workflow/i18n/es_PE.po
odoo/addons/sale_automatic_workflow/i18n/es_PY.po
odoo/addons/sale_automatic_workflow/i18n/es_VE.po
odoo/addons/sale_automatic_workflow/i18n/et.po
odoo/addons/sale_automatic_workflow/i18n/eu.po
odoo/addons/sale_automatic_workflow/i18n/fa.po
odoo/addons/sale_automatic_workflow/i18n/fi.po
odoo/addons/sale_automatic_workflow/i18n/fr.po
odoo/addons/sale_automatic_workflow/i18n/fr_CA.po
odoo/addons/sale_automatic_workflow/i18n/fr_CH.po
odoo/addons/sale_automatic_workflow/i18n/gl.po
odoo/addons/sale_automatic_workflow/i18n/gl_ES.po
odoo/addons/sale_automatic_workflow/i18n/he.po
odoo/addons/sale_automatic_workflow/i18n/hr.po
odoo/addons/sale_automatic_workflow/i18n/hr_HR.po
odoo/addons/sale_automatic_workflow/i18n/hu.po
odoo14_addon_sale_automatic_workflow-14.0.1.5.0.dist-info/METADATA
odoo14_addon_sale_automatic_workflow-14.0.1.5.0.dist-info/WHEEL
odoo14_addon_sale_automatic_workflow-14.0.1.5.0.dist-info/top_level.txt
odoo14_addon_sale_automatic_workflow-14.0.1.5.0.dist-info/RECORD
